phypy/__init__.py
phypy/analog.py
phypy/cli.py
phypy/corrections.py
phypy/dsp.py
phypy/modulators.py
phypy/structures.py
phypy/mimo/__init__.py
phypy/mimo/channels.py
phypy/mimo/mimo.py
phypy/mimo/precoders.py
phypy-0.2.8.dist-info/AUTHORS.rst
phypy-0.2.8.dist-info/LICENSE
phypy-0.2.8.dist-info/METADATA
phypy-0.2.8.dist-info/WHEEL
phypy-0.2.8.dist-info/entry_points.txt
phypy-0.2.8.dist-info/top_level.txt
phypy-0.2.8.dist-info/RECORD
