Metadata-Version: 2.1
Name: phypy
Version: 0.2.8
Summary: Library of tools for wireless, physical layer research, simulations, and testing.
Home-page: https://github.com/ctarver/phypy
Author: Chance Tarver
Author-email: tarver.chance@gmail.com
License: MIT license
Keywords: phypy
Platform: UNKNOWN
Classifier: Development Status :: 2 - Pre-Alpha
Classifier: Intended Audience :: Developers
Classifier: License :: OSI Approved :: MIT License
Classifier: Natural Language :: English
Classifier: Programming Language :: Python :: 3.6
Classifier: Programming Language :: Python :: 3.7
Requires-Python: >=3.6
Requires-Dist: Click (>=7.0)
Requires-Dist: numpy
